gpm/__init__.py
gpm/api.py
gpm/core.py
gpm/data.py
gpm/dates.py
gpm/old.py
prmte/__init__.py
prmte/api.py
prmte/core.py
prmte/data.py
tpower-0.1.6.dist-info/METADATA
tpower-0.1.6.dist-info/WHEEL
tpower-0.1.6.dist-info/top_level.txt
tpower-0.1.6.dist-info/RECORD
